dora_dataset_record/__init__.py
dora_dataset_record/__main__.py
dora_dataset_record/main.py
dora_dataset_record-0.1.0.dist-info/METADATA
dora_dataset_record-0.1.0.dist-info/WHEEL
dora_dataset_record-0.1.0.dist-info/entry_points.txt
dora_dataset_record-0.1.0.dist-info/top_level.txt
dora_dataset_record-0.1.0.dist-info/RECORD
