Metadata-Version: 2.4
Name: dora-dataset-record
Version: 0.1.0
Summary: dora-dataset-record
Author-email: Shashwat Patil <email@email.com>
License: MIT
Requires-Python: >=3.10
Requires-Dist: dora-rs>=0.3.9
Requires-Dist: pyarrow
Requires-Dist: lerobot[train]
